notion_scriba/__init__.py
notion_scriba/cli.py
notion_scriba/code_analyzer.py
notion_scriba/doc_generator.py
notion_scriba/interactive_mode.py
notion_scriba/notion_client.py
notion_scriba/setup_wizard.py
notion_scriba/templates.py
notion_scriba/llm/__init__.py
notion_scriba/llm/anthropic_provider.py
notion_scriba/llm/base.py
notion_scriba/llm/deepseek_provider.py
notion_scriba/llm/factory.py
notion_scriba/llm/google_provider.py
notion_scriba/llm/ollama_provider.py
notion_scriba/llm/openai_provider.py
notion_scriba-1.1.0.dist-info/licenses/LICENSE
notion_scriba-1.1.0.dist-info/METADATA
notion_scriba-1.1.0.dist-info/WHEEL
notion_scriba-1.1.0.dist-info/entry_points.txt
notion_scriba-1.1.0.dist-info/top_level.txt
notion_scriba-1.1.0.dist-info/RECORD
