Metadata-Version: 2.4
Name: notion-scriba
Version: 1.1.0
Summary: AI-powered documentation generator with multi-LLM support and Notion integration
Author-email: Davide Baldoni <davide@example.com>
License: GPL-3.0-or-later
Project-URL: Homepage, https://github.com/dbaldoni/notion-scriba
Project-URL: Documentation, https://github.com/dbaldoni/notion-scriba/blob/main/README.md
Project-URL: Repository, https://github.com/dbaldoni/notion-scriba
Project-URL: Issues, https://github.com/dbaldoni/notion-scriba/issues
Keywords: documentation,ai,llm,notion,openai,claude,gemini,gpl
Classifier: Development Status :: 4 - Beta
Classifier: Intended Audience :: Developers
Classifier: License :: OSI Approved :: GNU General Public License v3 or later (GPLv3+)
Classifier: Programming Language :: Python :: 3
Classifier: Programming Language :: Python :: 3.10
Classifier: Programming Language :: Python :: 3.11
Classifier: Programming Language :: Python :: 3.12
Classifier: Topic :: Software Development :: Documentation
Classifier: Topic :: Text Processing :: Markup :: Markdown
Requires-Python: >=3.10
License-File: LICENSE
Requires-Dist: requests>=2.31.0
Requires-Dist: python-dotenv>=1.0.0
Requires-Dist: pygments>=2.17.0
Requires-Dist: prompt-toolkit>=3.0.0
Requires-Dist: openai>=1.0.0
Requires-Dist: tiktoken>=0.5.0
Provides-Extra: anthropic
Requires-Dist: anthropic>=0.21.0; extra == "anthropic"
Provides-Extra: google
Requires-Dist: google-generativeai>=0.4.0; extra == "google"
Provides-Extra: all
Requires-Dist: anthropic>=0.21.0; extra == "all"
Requires-Dist: google-generativeai>=0.4.0; extra == "all"
Provides-Extra: dev
Requires-Dist: pytest>=7.4.0; extra == "dev"
Requires-Dist: pytest-cov>=4.1.0; extra == "dev"
Requires-Dist: black>=23.0.0; extra == "dev"
Requires-Dist: mypy>=1.7.0; extra == "dev"
Requires-Dist: ruff>=0.1.0; extra == "dev"
Dynamic: license-file
